twostock/__init__.py
twostock/py310/__init__.pyc
twostock/py310/cache_utils.pyc
twostock/py310/cert_utils.pyc
twostock/py310/common_permission.pyc
twostock/py310/config.pyc
twostock/py310/device_id.pyc
twostock/py310/formula.pyc
twostock/py310/general_api_wrapper.pyc
twostock/py310/token_utils.pyc
twostock/py311/__init__.pyc
twostock/py311/cache_utils.pyc
twostock/py311/cert_utils.pyc
twostock/py311/common_permission.pyc
twostock/py311/config.pyc
twostock/py311/device_id.pyc
twostock/py311/formula.pyc
twostock/py311/general_api_wrapper.pyc
twostock/py311/token_utils.pyc
twostock/py312/__init__.pyc
twostock/py312/cache_utils.pyc
twostock/py312/cert_utils.pyc
twostock/py312/common_permission.pyc
twostock/py312/config.pyc
twostock/py312/device_id.pyc
twostock/py312/formula.pyc
twostock/py312/general_api_wrapper.pyc
twostock/py312/token_utils.pyc
twostock/py313/__init__.pyc
twostock/py313/cache_utils.pyc
twostock/py313/cert_utils.pyc
twostock/py313/common_permission.pyc
twostock/py313/config.pyc
twostock/py313/device_id.pyc
twostock/py313/formula.pyc
twostock/py313/general_api_wrapper.pyc
twostock/py313/token_utils.pyc
twostock/py314/__init__.pyc
twostock/py314/cache_utils.pyc
twostock/py314/cert_utils.pyc
twostock/py314/common_permission.pyc
twostock/py314/config.pyc
twostock/py314/device_id.pyc
twostock/py314/formula.pyc
twostock/py314/general_api_wrapper.pyc
twostock/py314/token_utils.pyc
twostock/py38/__init__.pyc
twostock/py38/cache_utils.pyc
twostock/py38/cert_utils.pyc
twostock/py38/common_permission.pyc
twostock/py38/config.pyc
twostock/py38/device_id.pyc
twostock/py38/formula.pyc
twostock/py38/general_api_wrapper.pyc
twostock/py38/token_utils.pyc
twostock/py39/__init__.pyc
twostock/py39/cache_utils.pyc
twostock/py39/cert_utils.pyc
twostock/py39/common_permission.pyc
twostock/py39/config.pyc
twostock/py39/device_id.pyc
twostock/py39/formula.pyc
twostock/py39/general_api_wrapper.pyc
twostock/py39/token_utils.pyc
twostock-0.1025.0.dist-info/licenses/LICENSE
twostock-0.1025.0.dist-info/METADATA
twostock-0.1025.0.dist-info/WHEEL
twostock-0.1025.0.dist-info/top_level.txt
twostock-0.1025.0.dist-info/RECORD
